django_plpy/__init__.py
django_plpy/builder.py
django_plpy/installer.py
django_plpy/settings.py
django_plpy/utils.py
django_plpy/management/__init__.py
django_plpy/management/commands/__init__.py
django_plpy/management/commands/checkenv.py
django_plpy/management/commands/syncfunctions.py
django_plpy/migrations/0001_initial.py
django_plpy/migrations/__init__.py
django_plpy-0.1.0.dist-info/LICENSE.txt
django_plpy-0.1.0.dist-info/METADATA
django_plpy-0.1.0.dist-info/WHEEL
django_plpy-0.1.0.dist-info/top_level.txt
django_plpy-0.1.0.dist-info/RECORD
