Metadata-Version: 2.1
Name: django-plpy
Version: 0.1.0
Summary: Django utilities for Postgres PL/Python.
Home-page: https://github.com/eviltnan/django-plpy
Author: Thorin Schiffer
Author-email: thorin@schiffer.pro
License: MIT
Project-URL: Documentation, https://pyscaffold.org/
Project-URL: Source, https://github.com/eviltnan/django-plpy
Project-URL: Twitter, https://twitter.com/SchifferThorin
Platform: any
Classifier: Development Status :: 4 - Beta
Classifier: Programming Language :: Python
License-File: LICENSE.txt
Requires-Dist: django
Requires-Dist: psycopg2-binary
Requires-Dist: importlib-metadata ; python_version > "3.6"
Provides-Extra: testing
Requires-Dist: setuptools ; extra == 'testing'
Requires-Dist: pytest ; extra == 'testing'
Requires-Dist: pytest-cov ; extra == 'testing'
Requires-Dist: django-environ ; extra == 'testing'
Requires-Dist: tox ; extra == 'testing'
Requires-Dist: django-extensions ; extra == 'testing'
